library_analytics/__init__.py
library_analytics/analytics.py
library_analytics-0.1.0.dist-info/licenses/LICENSE
library_analytics-0.1.0.dist-info/METADATA
library_analytics-0.1.0.dist-info/WHEEL
library_analytics-0.1.0.dist-info/top_level.txt
library_analytics-0.1.0.dist-info/RECORD
