Metadata-Version: 2.4
Name: library-analytics
Version: 0.1.0
Summary: A Python package for library management analytics
Home-page: https://github.com/yourusername/library-analytics
Author: Your Name
Author-email: Your Name <your.email@example.com>
License: MIT
Project-URL: Homepage, https://github.com/yourusername/library-analytics
Project-URL: Repository, https://github.com/yourusername/library-analytics
Keywords: library,management,analytics,django,statistics
Classifier: Development Status :: 3 - Alpha
Classifier: Intended Audience :: Developers
Classifier: Topic :: Software Development :: Libraries :: Python Modules
Classifier: License :: OSI Approved :: MIT License
Classifier: Programming Language :: Python :: 3
Classifier: Programming Language :: Python :: 3.8
Classifier: Programming Language :: Python :: 3.9
Classifier: Programming Language :: Python :: 3.10
Classifier: Programming Language :: Python :: 3.11
Classifier: Programming Language :: Python :: 3.12
Classifier: Framework :: Django
Requires-Python: >=3.8
License-File: LICENSE
Provides-Extra: django
Requires-Dist: Django>=4.0; extra == "django"
Dynamic: author
Dynamic: home-page
Dynamic: license-file
Dynamic: requires-python
